domeneshop_bots/DNSBot.py
domeneshop_bots/__init__.py
domeneshop_bots/helper.py
tests/DNSBotTest.py
tests/__init__.py
domeneshop_bots-0.0.2.dist-info/LICENSE
domeneshop_bots-0.0.2.dist-info/METADATA
domeneshop_bots-0.0.2.dist-info/WHEEL
domeneshop_bots-0.0.2.dist-info/top_level.txt
domeneshop_bots-0.0.2.dist-info/RECORD
