Metadata-Version: 2.1
Name: domeneshop-bots
Version: 0.0.2
Summary: Bot for domeneshop.no to keep your dns records updated with correct ip for your self hosting sites and services
Home-page: https://github.com/larsensolutions/domeneshop-bots
Author: Erik Larsen
Author-email: eriklarsen.post@gmail.com
License: UNKNOWN
Platform: UNKNOWN
Classifier: Programming Language :: Python :: 3
Classifier: License :: OSI Approved :: MIT License
Classifier: Operating System :: OS Independent
Requires-Python: >=3.6
Requires-Dist: requests
Requires-Dist: jsonschema
Requires-Dist: schedule
Requires-Dist: domeneshop
